<?xml version="1.0" encoding="utf-8" standalone="no" ?>
<modDesc descVersion="40">
	<author>Ls-Modcompany - kevink98</author>
    <version>0.1.0.0</version>
    <title>
        <en>GlobalCompany</en>
    </title>
    <description>
        <de><![CDATA[GlobalCompany]]></de>
		<en><![CDATA[GlobalCompany]]></en>

    </description>
    <iconFilename>globalCompany.dds</iconFilename>
    <multiplayer supported="true"/>
	<extraSourceFiles>	
		<sourceFile filename="GlobalCompany.lua" /> 
	</extraSourceFiles>

    <l10n>		
		<text name="input_GC_BALESHREADER_TURNON_AREALIGHTS"><en>turnAreaLights</en></text>
		<text name="input_GC_MAIN"><en>GlobalCompany</en><de>GlobalCompany</de></text>
		<text name="input_GC_GREENHOUSE_VENTILATOR"><en>greenhouse ventilator</en></text>
		<text name="input_GC_BALEADDON_CUT"><en>Cut Bale</en><de>Ballen aufschneiden</de></text>
	</l10n>		
	
	<actions>
        <action name="GC_BALESHREADER_TURNON_AREALIGHTS" />
        <action name="GC_MAIN" />
        <action name="GC_GREENHOUSE_VENTILATOR" />
		<action name="GC_BALEADDON_CUT" />
    </actions>

    <inputBinding>
        <actionBinding action="GC_BALESHREADER_TURNON_AREALIGHTS">
            <binding device="KB_MOUSE_DEFAULT" input="KEY_f" axisComponent="+" neutralInput="0" index="1"/>
            <binding device="0_XINPUT_GAMEPAD" input="BUTTON_6 BUTTON_3" axisComponent="+" neutralInput="0" index="1"/>
        </actionBinding>   
        <actionBinding action="GC_MAIN">
            <binding device="KB_MOUSE_DEFAULT" input="KEY_lctrl KEY_g" axisComponent="+" neutralInput="0" index="1"/>
        </actionBinding> 
        <actionBinding action="GC_GREENHOUSE_VENTILATOR">
            <binding device="KB_MOUSE_DEFAULT" input="KEY_b" axisComponent="+" neutralInput="0" index="1"/>
        </actionBinding>
        <actionBinding action="GC_BALEADDON_CUT">
            <binding device="KB_MOUSE_DEFAULT" input="MOUSE_BUTTON_RIGHT" axisComponent="+" neutralInput="0" index="3"/>
        </actionBinding>		
    </inputBinding>
    
    

</modDesc>